{
  "name": "OHR.Buritaca_ZH-CN7178457066",
  "urlbase": "/th?id=OHR.Buritaca_ZH-CN7178457066",
  "copyright_cn": "风景秀丽的加勒比海岸，哥伦比亚 (© Nicholas Hills/Getty Images)",
  "copyrightlink": "/search?q=%e5%93%a5%e4%bc%a6%e6%af%94%e4%ba%9a&form=hpcapt&mkt=zh-cn",
  "desc": "Central America becomes South America at the shores of Colombia, the northernmost country in South America. Colombia is the only country in South America that has coastline on both the Caribbean Sea to the east and the Pacific Ocean to the west. Seen here is a stretch of beach near Buritaca, on the Caribbean side of Colombia. This region of Colombia boasts some of the most beautiful beaches in the country. It is also among the country's most ecologically diverse with jungle, desert, and the highest coastal mountain range in the world, the Sierra Nevada.",
  "copyright": "Caribbean coast near Buritaca, Colombia (© Nicholas Hills/Getty Images)",
  "raw_size": "3708x2086",
  "url": {
    "UHD": "https://www.bing.com/th?id=OHR.Buritaca_ZH-CN7178457066_UHD.jpg",
    "1920x1080": "https://www.bing.com/th?id=OHR.Buritaca_ZH-CN7178457066_1920x1080.jpg",
    "1024x768": "https://www.bing.com/th?id=OHR.Buritaca_ZH-CN7178457066_1024x768.jpg",
    "1366x768": "https://www.bing.com/th?id=OHR.Buritaca_ZH-CN7178457066_1366x768.jpg",
    "800x480": "https://www.bing.com/th?id=OHR.Buritaca_ZH-CN7178457066_800x480.jpg",
    "1080x1920": "https://www.bing.com/th?id=OHR.Buritaca_ZH-CN7178457066_1080x1920.jpg",
    "480x800": "https://www.bing.com/th?id=OHR.Buritaca_ZH-CN7178457066_480x800.jpg"
  },
  "telegram": {
    "archive": {
      "UHD": {
        "message_id": 1057,
        "file_id": "BQACAgUAAx0EZTyx0QACBCFiQrypW53gV6G5mvUO_AHCU3cTNQACGgUAAiODGFZNpnuLcvtntyME"
      },
      "1920x1080": {
        "message_id": 1058,
        "file_id": "BQACAgUAAx0EZTyx0QACBCJiQrysQ5UeUaT2OKDLrWUMCoDb0wACGwUAAiODGFYYzQtF3k7QViME"
      },
      "1024x768": {
        "message_id": 1059,
        "file_id": "BQACAgUAAx0EZTyx0QACBCNiQrytFUNYU1wvuLJFfOJOtXrsUQACHAUAAiODGFYgLrel6liwrSME"
      },
      "1366x768": {
        "message_id": 1060,
        "file_id": "BQACAgUAAx0EZTyx0QACBCRiQryv7hEyYFAllmNxNl2PiBlDKgACHQUAAiODGFYLZK0CSrJH-SME"
      },
      "800x480": {
        "message_id": 1061,
        "file_id": "BQACAgUAAx0EZTyx0QACBCViQrywJB7AWD2BzckCb5aolrEd_QACHgUAAiODGFbrup3efbdvmCME"
      },
      "1080x1920": {
        "message_id": 1062,
        "file_id": "BQACAgUAAx0EZTyx0QACBCZiQryyvk-G5k5ET6iVg2KtPZw6RQACHwUAAiODGFYDLfnyOpHOiiME"
      },
      "480x800": {
        "message_id": 1063,
        "file_id": "BQACAgUAAx0EZTyx0QACBCdiQry0GgXaZUoB4C3zIxaeM4igJgACIAUAAiODGFYYdrsGEFnZlCME"
      }
    },
    "photo": [
      {
        "file_id": "AgACAgUAAx0EZTyx0QACBCliQry2SAABnn6GDcnCHuEXgHAediAAAjywMRsjgxhWYP32XuXrnroBAAMCAANzAAMjBA",
        "file_unique_id": "AQADPLAxGyODGFZ4",
        "file_size": 1346,
        "width": 90,
        "height": 51
      },
      {
        "file_id": "AgACAgUAAx0EZTyx0QACBCliQry2SAABnn6GDcnCHuEXgHAediAAAjywMRsjgxhWYP32XuXrnroBAAMCAANtAAMjBA",
        "file_unique_id": "AQADPLAxGyODGFZy",
        "file_size": 27922,
        "width": 320,
        "height": 180
      },
      {
        "file_id": "AgACAgUAAx0EZTyx0QACBCliQry2SAABnn6GDcnCHuEXgHAediAAAjywMRsjgxhWYP32XuXrnroBAAMCAAN4AAMjBA",
        "file_unique_id": "AQADPLAxGyODGFZ9",
        "file_size": 163861,
        "width": 800,
        "height": 450
      },
      {
        "file_id": "AgACAgUAAx0EZTyx0QACBCliQry2SAABnn6GDcnCHuEXgHAediAAAjywMRsjgxhWYP32XuXrnroBAAMCAAN3AAMjBA",
        "file_unique_id": "AQADPLAxGyODGFZ8",
        "file_size": 341981,
        "width": 1920,
        "height": 1080
      },
      {
        "file_id": "AgACAgUAAx0EZTyx0QACBCliQry2SAABnn6GDcnCHuEXgHAediAAAjywMRsjgxhWYP32XuXrnroBAAMCAAN5AAMjBA",
        "file_unique_id": "AQADPLAxGyODGFZ-",
        "file_size": 409790,
        "width": 1280,
        "height": 720
      }
    ]
  }
}